MANIFEST.in
README.rst
setup.py
macrocast/__init__.py
macrocast.egg-info/PKG-INFO
macrocast.egg-info/SOURCES.txt
macrocast.egg-info/dependency_links.txt
macrocast.egg-info/not-zip-safe
macrocast.egg-info/top_level.txt