Metadata-Version: 1.1
Name: macrocast
Version: 0.0.2
Summary: A forecasting package for macroeconomic data
Home-page: http://www.amirsani.com
Author: Amir Sani
Author-email: reachme@amirsani.com
License: UNKNOWN
Download-URL: https://github.com/amirsani/macrocast
Platform: UNKNOWN
